.DS_Store
.gitignore
.pre-commit-config.yaml
CONTRIBUTING.md
LICENSE.txt
MANIFEST.in
README.md
generate_pycharm_configs.py
requirements.txt
setup.py
.github/workflows/custom-image.yml
.github/workflows/django_tests.yml
.github/workflows/scancode-toolkit.yml
.github/workflows/vulnerability-scan.yml
lex/.DS_Store
lex/.dockerignore
lex/.gardenignore
lex/.gitignore
lex/.gitmodules
lex/.gitpod.yml
lex/__init__.py
lex/__main__.py
lex/manage.py
lex/proxy.py
lex/reproduce_issue.py
lex/streamlit_app.py
lex/.streamlit/config.toml
lex/.vscode/launch.json
lex/.vscode/settings.json
lex/api/__init__.py
lex/api/admin.py
lex/api/apps.py
lex/api/models.py
lex/api/views.py
lex/api/consumers/BackendHealthConsumer.py
lex/api/consumers/CalculationLogConsumer.py
lex/api/consumers/CalculationsConsumer.py
lex/api/consumers/LogConsumer.py
lex/api/consumers/UpdateCalculationStatusConsumer.py
lex/api/consumers/__init__.py
lex/api/fields/Bokeh_field.py
lex/api/fields/HTML_field.py
lex/api/fields/PDF_field.py
lex/api/fields/XLSX_field.py
lex/api/fields/__init__.py
lex/api/filters/__init__.py
lex/api/filters/filter_tree.py
lex/api/filters/generic_filters.py
lex/api/middleware/__init__.py
lex/api/middleware/keycloak_permissions.py
lex/api/migrations/__init__.py
lex/api/serializers/__init__.py
lex/api/serializers/base_serializers.py
lex/api/utils/__init__.py
lex/api/utils/collection_utils.py
lex/api/utils/context.py
lex/api/utils/converters.py
lex/api/utils/helpers.py
lex/api/views/__init__.py
lex/api/views/model_relation_views.py
lex/api/views/pagination.py
lex/api/views/utils.py
lex/api/views/LexLoggerView/LexLoggerView.py
lex/api/views/LexLoggerView/__init__.py
lex/api/views/authentication/KeycloakManager.py
lex/api/views/authentication/UserAPIView.py
lex/api/views/authentication/UserPermissionView.py
lex/api/views/authentication/__init__.py
lex/api/views/authentication/auth.py
lex/api/views/authentication/helpers.py
lex/api/views/authentication/token_views.py
lex_app.egg-info/PKG-INFO
lex_app.egg-info/SOURCES.txt
lex_app.egg-info/dependency_links.txt
lex_app.egg-info/entry_points.txt
lex_app.egg-info/requires.txt
lex_app.egg-info/top_level.txt