Metadata-Version: 2.4
Name: lex-app
Version: 2.0.0rc22
Summary: A Python / Django library to create business applications easily with complex logic
Home-page: https://github.com/ExcellenceCloudGmbH/lex-app
Author: Melih Sünbül
Author-email: m.sunbul@excellence-cloud.com
Classifier: Programming Language :: Python :: 3
Classifier: License :: OSI Approved :: MIT License
Classifier: Operating System :: OS Independent
Requires-Python: >=3.6
License-File: LICENSE.txt
Requires-Dist: starlette
Requires-Dist: httpx
Requires-Dist: authlib
Requires-Dist: itsdangerous
Requires-Dist: django
Requires-Dist: django-cors-headers
Requires-Dist: djangorestframework-api-key
Requires-Dist: django-filter
Requires-Dist: XlsxWriter
Requires-Dist: pandas
Requires-Dist: openpyxl
Requires-Dist: djangorestframework
Requires-Dist: django-sendgrid-v5
Requires-Dist: redis
Requires-Dist: celery
Requires-Dist: python-dotenv
Requires-Dist: sentry_sdk
Requires-Dist: channels
Requires-Dist: asyncio
Requires-Dist: channels-redis
Requires-Dist: uvicorn[standard]
Requires-Dist: nest_asyncio
Requires-Dist: Office365-REST-Python-Client
Requires-Dist: streamlit
Requires-Dist: streamlit-keycloak-lex
Requires-Dist: sqlalchemy
Requires-Dist: django_redis
Requires-Dist: django-storages[google]
Requires-Dist: DjangoSharepointStorage==1.1.3
Requires-Dist: click
Requires-Dist: django-lifecycle
Requires-Dist: python-keycloak==3.9.1
Requires-Dist: markdown
Requires-Dist: mistune
Requires-Dist: django-simple-history
Requires-Dist: markdown2
Requires-Dist: xhtml2pdf
Requires-Dist: tabulate
Requires-Dist: django-db-views
Requires-Dist: pre-commit
Requires-Dist: factory-boy
Requires-Dist: coverage
Requires-Dist: django-oauth2-codeflow
Requires-Dist: psycopg2-binary
Requires-Dist: django-celery-beat
Dynamic: author
Dynamic: author-email
Dynamic: classifier
Dynamic: description-content-type
Dynamic: home-page
Dynamic: license-file
Dynamic: requires-dist
Dynamic: requires-python
Dynamic: summary
